{"name":"123456","children":[{"name":"\u7f8e\u597d\u5e74\u4ee3","id":"528170964050484","link":"https:\/\/www.facebook.com\/CTIAGoodDay\/","size":"33085","number":"14008"},{"name":"\u65b0\u6ce8\u97f3\u65b0\u805e","id":"255223767942122","link":"https:\/\/www.facebook.com\/\u65b0\u6ce8\u97f3\u65b0\u805e-255223767942122\/","size":"36546","number":"12018"},{"name":"\u7d93\u6fdf\u4e00\u9031","id":"192631997435713","link":"https:\/\/www.facebook.com\/edigest\/","size":"38911","number":"13275"},{"name":"\u65b0\u805e\u6df1\u5589\u56a8","id":"139477149725137","link":"https:\/\/www.facebook.com\/DeepThroatNews\/","size":"45537","number":"18123"},{"name":"\u5fc5\u52dd\u7df4\u7fd2\u751f","id":"1182662801752445","link":"https:\/\/www.facebook.com\/LoveByDesign2016\/","size":"50980","number":"18856"},{"name":"\u690d\u5287\u5834","id":"484056911755566","link":"https:\/\/www.facebook.com\/Qseries2016\/","size":"68607","number":"30033"},{"name":"\u4e09\u7acb\u83ef\u5287\uff0d\u72fc\u738b\u5b50 Prince Of Wolf","id":"286787608326701","link":"https:\/\/www.facebook.com\/SETPrinceOfWolf\/","size":"114566","number":"48856"},{"name":"\u98db\u9b5a\u9ad8\u6821\u751f Swimming Battle","id":"1749128292011537","link":"https:\/\/www.facebook.com\/SETSwimmingBattle\/","size":"115439","number":"50383"},{"name":"\u5f6d\u653f\u9594\u5f8c\u63f4\u6703","id":"132148736852993","link":"https:\/\/www.facebook.com\/PENG.C.M\/","size":"116062","number":"36429"},{"name":"KISSRADIO","id":"261352204950","link":"https:\/\/www.facebook.com\/KISSNET\/","size":"118991","number":"55772"},{"name":"\u4e2d\u6642\u96fb\u5b50\u5831\u300c\u8996\u983b\u300d","id":"329118253934643","link":"https:\/\/www.facebook.com\/chinatimes.com.tw\/","size":"189110","number":"96167"},{"name":"\u65b0\u805e\u9f8d\u6372\u98a8","id":"396741173751746","link":"https:\/\/www.facebook.com\/52tornado\/","size":"222432","number":"172373"},{"name":"\u98b1\u98a8\u5927\u8086\u8650","id":"144395872245335","link":"https:\/\/www.facebook.com\/TYPHOONJP\/","size":"330890","number":"395714"},{"name":"CMoney \u6295\u8cc7\u8a8c","id":"257021031115648","link":"https:\/\/www.facebook.com\/cmoneyapp2\/","size":"498438","number":"154207"},{"name":"\u95dc\u9375\u6642\u523b","id":"106154352764107","link":"https:\/\/www.facebook.com\/CTimefans\/","size":"727172","number":"330963"},{"name":"\u58f9\u9031\u520a","id":"125693144152226","link":"https:\/\/www.facebook.com\/nexttw\/","size":"1670320","number":"604822"}]}