{"name":"123456","children":[{"name":"Sangpuy \u6851\u5e03\u4f0a","id":"405182689517991","link":"https:\/\/www.facebook.com\/Sangpuy\/","size":"11940","number":"2835"},{"name":"\u5c0f\u8056\u868a\u7684\u6cbb\u570b\u65e5\u8a18","id":"1468466990097623","link":"https:\/\/www.facebook.com\/HolyMosquito\/","size":"64282","number":"20502"},{"name":"\u53e4\u5178\u597d\u597d\u807d  Classicalmusic to go","id":"274373446072","link":"https:\/\/www.facebook.com\/taiwanclassicalmusic\/","size":"148517","number":"44822"},{"name":"\u9673\u5609\u6a3a Ella","id":"322372034467971","link":"https:\/\/www.facebook.com\/himella\/","size":"1333636","number":"882984"}]}